tinymce/__init__.py
tinymce/apps.py
tinymce/models.py
tinymce/settings.py
tinymce/urls.py
tinymce/views.py
tinymce/widgets.py
tinymce/static/tinymce/css/prism.css
tinymce/static/tinymce/js/prism.js
tinymce/static/tinymce/js/tinymce/jquery.tinymce.min.js
tinymce/static/tinymce/js/tinymce/license.txt
tinymce/static/tinymce/js/tinymce/tiny_mce_popup.js
tinymce/static/tinymce/js/tinymce/tinymce.gzip.js
tinymce/static/tinymce/js/tinymce/tinymce.min.js
tinymce/static/tinymce/js/tinymce/langs/af_ZA.js
tinymce/static/tinymce/js/tinymce/langs/ar.js
tinymce/static/tinymce/js/tinymce/langs/ar_SA.js
tinymce/static/tinymce/js/tinymce/langs/az.js
tinymce/static/tinymce/js/tinymce/langs/be.js
tinymce/static/tinymce/js/tinymce/langs/bg_BG.js
tinymce/static/tinymce/js/tinymce/langs/bn_BD.js
tinymce/static/tinymce/js/tinymce/langs/bs.js
tinymce/static/tinymce/js/tinymce/langs/ca.js
tinymce/static/tinymce/js/tinymce/langs/cs.js
tinymce/static/tinymce/js/tinymce/langs/cs_CZ.js
tinymce/static/tinymce/js/tinymce/langs/cy.js
tinymce/static/tinymce/js/tinymce/langs/da.js
tinymce/static/tinymce/js/tinymce/langs/de.js
tinymce/static/tinymce/js/tinymce/langs/de_AT.js
tinymce/static/tinymce/js/tinymce/langs/dv.js
tinymce/static/tinymce/js/tinymce/langs/el.js
tinymce/static/tinymce/js/tinymce/langs/en_CA.js
tinymce/static/tinymce/js/tinymce/langs/en_GB.js
tinymce/static/tinymce/js/tinymce/langs/eo.js
tinymce/static/tinymce/js/tinymce/langs/es.js
tinymce/static/tinymce/js/tinymce/langs/es_MX.js
tinymce/static/tinymce/js/tinymce/langs/et.js
tinymce/static/tinymce/js/tinymce/langs/eu.js
tinymce/static/tinymce/js/tinymce/langs/fa.js
tinymce/static/tinymce/js/tinymce/langs/fa_IR.js
tinymce/static/tinymce/js/tinymce/langs/fi.js
tinymce/static/tinymce/js/tinymce/langs/fo.js
tinymce/static/tinymce/js/tinymce/langs/fr_CH.js
tinymce/static/tinymce/js/tinymce/langs/fr_FR.js
tinymce/static/tinymce/js/tinymce/langs/ga.js
tinymce/static/tinymce/js/tinymce/langs/gd.js
django_tinymce4_lite-1.7.5.dist-info/LICENSE.txt
django_tinymce4_lite-1.7.5.dist-info/METADATA
django_tinymce4_lite-1.7.5.dist-info/WHEEL
django_tinymce4_lite-1.7.5.dist-info/top_level.txt
django_tinymce4_lite-1.7.5.dist-info/RECORD
