Metadata-Version: 1.1
Name: django-tinymce4-lite
Version: 1.7.5
Summary: A Django application that provides a fully functional TinyMCE 4 editor widget for models and forms.
Home-page: https://github.com/romanvm/django-tinymce4-lite
Author: Roman Miroshnychenko (fork author)
Author-email: roman1972@gmail.com
License: MIT License
Keywords: django wysiwyg editor widget tinymce
Platform: any
Classifier: Development Status :: 5 - Production/Stable
Classifier: Environment :: Web Environment
Classifier: Framework :: Django
Classifier: Intended Audience :: Developers
Classifier: License :: OSI Approved :: MIT License
Classifier: Operating System :: OS Independent
Classifier: Programming Language :: Python
Classifier: Programming Language :: Python :: 2.7
Classifier: Programming Language :: Python :: 3
Classifier: Framework :: Django
Classifier: Framework :: Django :: 1.11
Classifier: Framework :: Django :: 2.0
Classifier: Framework :: Django :: 2.1
Classifier: Topic :: Software Development :: Libraries :: Application Frameworks
Classifier: Topic :: Software Development :: Libraries :: Python Modules
